autoformalism_with_llms/__about__.py
autoformalism_with_llms/__init__.py
autoformalism_with_llms/config.py
autoformalism_with_llms/dataset.py
autoformalism_with_llms/prompt.py
autoformalism_with_llms-0.0.1.dist-info/METADATA
autoformalism_with_llms-0.0.1.dist-info/WHEEL
autoformalism_with_llms-0.0.1.dist-info/licenses/LICENSE.txt
autoformalism_with_llms-0.0.1.dist-info/RECORD
